Metadata-Version: 2.1
Name: benchmarx
Version: 0.1.0
Summary: Tools for benchmarking optimization methods
Home-page: https://github.com/AlexToW/benchmarx
Author: AlexToW
Author-email: Salex <31salex31@gmail.com>
License: MIT
Project-URL: Homepage, https://github.com/AlexToW/benchmarx
Project-URL: Bug Tracker, https://github.com/AlexToW/benchmarx/issues
Classifier: Programming Language :: Python :: 3.7
Classifier: License :: OSI Approved :: MIT License
Classifier: Operating System :: OS Independent
Requires-Python: >=3.7
License-File: LICENSE
Requires-Dist: hatchling
Requires-Dist: jax
Requires-Dist: jaxopt (>=0.6)
Requires-Dist: typing-extensions (>=4.5.0)
Requires-Dist: wandb (>=0.14.2)
Requires-Dist: pandas (==1.5.3)
Requires-Dist: plotly (>=5.14.1)
Requires-Dist: flax (>=0.6.10)
Requires-Dist: tensorflow-datasets
